scrolls/__init__.py
scrolls/clock.py
scrolls/configuration.py
scrolls/dependencies.py
scrolls/entrypoint.py
scrolls/filesystem.py
scrolls/idresolver.py
scrolls/importer.py
scrolls/listener.py
scrolls/log.py
scrolls/rsyslog.py
scrolls/security.py
scrolls/server.py
scrolls/factories/__init__.py
scrolls/factories/counter.py
scrolls/factories/message.py
scrolls/models/__init__.py
scrolls/models/counter.py
scrolls/models/filter.py
scrolls/models/message.py
scrolls/models/root.py
scrolls/parsers/__init__.py
scrolls/parsers/baseparser.py
scrolls/parsers/nginx.py
scrolls/parsers/rsyslog.py
scrolls/parsers/useragent.py
scrolls/repositories/__init__.py
scrolls/repositories/message.py
scrolls/repositories/statistic.py
scrolls/static/home.css
scrolls/templates/login.jinja2
scrolls/templates/master.jinja2
scrolls/templates/message.jinja2
scrolls/templates/messages.jinja2
scrolls/views/__init__.py
scrolls/views/authentication.py
scrolls/views/home.py
scrolls/views/protected.py
scrolls-0.0.4823123.dist-info/DESCRIPTION.rst
scrolls-0.0.4823123.dist-info/LICENSE.txt
scrolls-0.0.4823123.dist-info/METADATA
scrolls-0.0.4823123.dist-info/RECORD
scrolls-0.0.4823123.dist-info/WHEEL
scrolls-0.0.4823123.dist-info/entry_points.txt
scrolls-0.0.4823123.dist-info/metadata.json
scrolls-0.0.4823123.dist-info/top_level.txt
test/__init__.py
test/authenticationview_tests.py
test/clockmock.py
test/configuration_tests.py
test/counter_tests.py
test/counterfactory_tests.py
test/dependencies_tests.py
test/ditestcase.py
test/entrypoint_tests.py
test/filesystem_tests.py
test/filter_tests.py
test/homeview_tests.py
test/idresolver_tests.py
test/importer_tests.py
test/listener_tests.py
test/log_tests.py
test/message_tests.py
test/messagefactory_tests.py
test/messagerepository_tests.py
test/nginxparser_tests.py
test/protectedview_tests.py
test/redirectioncontextmanager.py
test/root_tests.py
test/rsyslog_tests.py
test/rsyslogparser_tests.py
test/security_tests.py
test/servermock.py
test/statisticrepository_tests.py
test/useragentparser_tests.py
test/viewtestcase.py
