Metadata-Version: 2.0
Name: scrolls
Version: 0.0.4823123
Summary: Log manager.
Home-page: https://github.com/ilogue/scrolls
Author: Jasper J.F. van den Bosch
Author-email: japsai@gmail.com
License: UNKNOWN
Platform: UNKNOWN
Classifier: Programming Language :: Python
Classifier: Framework :: Pyramid
Classifier: Topic :: Internet :: WWW/HTTP
Classifier: Topic :: Internet :: WWW/HTTP :: WSGI :: Application
Requires-Dist: coverage
Requires-Dist: mock
Requires-Dist: pyramid
Requires-Dist: pyramid-jinja2
Requires-Dist: python-dateutil
Requires-Dist: ua-parser
Requires-Dist: waitress
Requires-Dist: wheel
